{
	"configurations" : 
	[
		{
			"directories" : 
			[
				{
					"build" : ".",
					"jsonFile" : "directory-.-Debug-f5ebdc15457944623624.json",
					"minimumCMakeVersion" : 
					{
						"string" : "3.21"
					},
					"projectIndex" : 0,
					"source" : ".",
					"targetIndexes" : 
					[
						0
					]
				}
			],
			"name" : "Debug",
			"projects" : 
			[
				{
					"directoryIndexes" : 
					[
						0
					],
					"name" : "mart_monteCarlo",
					"targetIndexes" : 
					[
						0
					]
				}
			],
			"targets" : 
			[
				{
					"directoryIndex" : 0,
					"id" : "mart_monteCarlo::@6890427a1f51a3e7e1df",
					"jsonFile" : "target-mart_monteCarlo-Debug-ec63be068ecb9fccc5b5.json",
					"name" : "mart_monteCarlo",
					"projectIndex" : 0
				}
			]
		}
	],
	"kind" : "codemodel",
	"paths" : 
	{
		"build" : "/Users/joshcai/CLionProjects/mart_monteCarlo/cmake-build-debug",
		"source" : "/Users/joshcai/CLionProjects/mart_monteCarlo"
	},
	"version" : 
	{
		"major" : 2,
		"minor" : 3
	}
}
